{
  "data": [
    {
      "title": "Projects",
      "subTitle": "Tope Dare Foundation",
      "imgLink": "https://i.ibb.co/DGBPBh0/DSCA0905.jpg"
    },
    {
      "title": "Projects",
      "subTitle": "Tope Dare Foundation",
      "imgLink": "https://i.ibb.co/0tH2xkG/DSCA0786.jpg"
    },
    {
      "title": "Projects",
      "subTitle": "Tope Dare Foundation",
      "imgLink": "https://i.ibb.co/rvXxJBB/DSCA0736.jpg"
    },
    {
      "title": "Projects",
      "subTitle": "Tope Dare Foundation",
      "imgLink": "https://i.ibb.co/w7xdCfJ/DSCF1961.jpg"
    },
    {
      "title": "Projects",
      "subTitle": "Tope Dare Foundation",
      "imgLink": "https://i.ibb.co/tYqNy1t/DSCA0796.jpg"
    },
    {
      "title": "Projects",
      "subTitle": "Tope Dare Foundation",
      "imgLink": "https://i.ibb.co/R7dBHpF/DSCA0871.jpg"
    },
    {
      "title": "Projects",
      "subTitle": "Tope Dare Foundation",
      "imgLink": "https://i.ibb.co/4JJrYNt/DSCA0888.jpg"
    },
    {
      "title": "Projects",
      "subTitle": "Tope Dare Foundation",
      "imgLink": "https://i.ibb.co/DGBPBh0/DSCA0905.jpg"
    },
    {
      "title": "Projects",
      "subTitle": "Tope Dare Foundation",
      "imgLink": "https://i.ibb.co/8s1hp77/DSCA0922.jpg"
    },
    {
      "title": "Projects",
      "subTitle": "Tope Dare Foundation",
      "imgLink": "https://i.ibb.co/cF1XvNz/DSCA0953.jpg"
    },
    {
      "title": "Projects",
      "subTitle": "Tope Dare Foundation",
      "imgLink": "https://i.ibb.co/2YDDCGW/DSCF1873.jpg"
    },
    {
      "title": "Projects",
      "subTitle": "Tope Dare Foundation",
      "imgLink": "https://i.ibb.co/w7xdCfJ/DSCF1961.jpg"
    },
    {
      "title": "Projects",
      "subTitle": "Tope Dare Foundation",
      "imgLink": "https://i.ibb.co/LC0s1Jp/DSCF1976.jpg"
    },
    {
      "title": "Projects",
      "subTitle": "Tope Dare Foundation",
      "imgLink": "https://i.ibb.co/yXjhKX9/DSCF2016.jpg"
    },
    {
      "title": "Projects",
      "subTitle": "Tope Dare Foundation",
      "imgLink": "https://i.ibb.co/fxvXWnX/DSCF2049.jpg"
    },
    {
      "title": "Projects",
      "subTitle": "Tope Dare Foundation",
      "imgLink": "https://i.ibb.co/HnrTH73/DSCF2073.jpg"
    },
    {
      "title": "Projects",
      "subTitle": "Tope Dare Foundation",
      "imgLink": "https://i.ibb.co/VSxQfBj/DSCF2076.jpg"
    },
    {
      "title": "Projects",
      "subTitle": "Tope Dare Foundation",
      "imgLink": "https://i.ibb.co/yhdkV0b/DSCF2152.jpg"
    },
    {
      "title": "Projects",
      "subTitle": "Tope Dare Foundation",
      "imgLink": "https://i.ibb.co/FspR0DQ/DSCF2572.jpg"
    },
    {
      "title": "Projects",
      "subTitle": "Tope Dare Foundation",
      "imgLink": "https://i.ibb.co/FWmDXk0/DSCF2579.jpg"
    },
    {
      "title": "Projects",
      "subTitle": "Tope Dare Foundation",
      "imgLink": "https://i.ibb.co/KymGNBH/DSCF2824.jpg"
    },
    {
      "title": "Projects",
      "subTitle": "Tope Dare Foundation",
      "imgLink": "https://i.ibb.co/PrffMrV/DSCF2835.jpg"
    },
    {
      "title": "Projects",
      "subTitle": "Tope Dare Foundation",
      "imgLink": "https://i.ibb.co/Bcp8Lhs/tope-dare-foundation-project-4.jpg"
    },
    {
      "title": "Projects",
      "subTitle": "Tope Dare Foundation",
      "imgLink": "https://i.ibb.co/LYcp31L/tope-dare-foundation-project-1.jpg"
    },
    {
      "title": "Projects",
      "subTitle": "Tope Dare Foundation",
      "imgLink": "https://i.ibb.co/Bcp8Lhs/tope-dare-foundation-project-4.jpg"
    },
    {
      "title": "Projects",
      "subTitle": "Tope Dare Foundation",
      "imgLink": "https://i.ibb.co/H4FHkF0/tope-dare-foundation-project-3.jpg"
    },
    {
      "title": "Projects",
      "subTitle": "Tope Dare Foundation",
      "imgLink": "https://i.ibb.co/9G12DCt/tope-dare-foundation-project-5.jpg"
    },
    {
      "title": "Projects",
      "subTitle": "Tope Dare Foundation",
      "imgLink": "https://i.ibb.co/VDP0f1R/tope-dare-foundation-project-6.jpg"
    },
    {
      "title": "Projects",
      "subTitle": "Tope Dare Foundation",
      "imgLink": "https://i.ibb.co/FK22Nqy/tope-dare-foundation-project-7.jpg"
    },
    {
      "title": "Projects",
      "subTitle": "Tope Dare Foundation",
      "imgLink": "https://i.ibb.co/cNDxrZp/tope-dare-foundation-project-9.jpg"
    },
    {
      "title": "Projects",
      "subTitle": "Tope Dare Foundation",
      "imgLink": "https://i.ibb.co/VT08Ljc/tope-dare-foundation-project-10.jpg"
    },
    {
      "title": "Projects",
      "subTitle": "Tope Dare Foundation",
      "imgLink": "https://i.ibb.co/ftMphJw/project-1.jpg"
    },
    {
      "title": "Projects",
      "subTitle": "Tope Dare Foundation",
      "imgLink": "https://i.ibb.co/VJDkwcz/school-children.jpg"
    },
    {
      "title": "Projects",
      "subTitle": "Tope Dare Foundation",
      "imgLink": "https://i.ibb.co/jHRcSGK/project-3.jpg"
    },
    {
      "title": "Projects",
      "subTitle": "Tope Dare Foundation",
      "imgLink": "https://i.ibb.co/Xp3yvhY/project-2.jpg"
    }
  ]
}
